Simplextep/Simplextep.py
Simplextep/__init__.py
Simplextep-1.13.4.dist-info/LICENSE
Simplextep-1.13.4.dist-info/METADATA
Simplextep-1.13.4.dist-info/WHEEL
Simplextep-1.13.4.dist-info/top_level.txt
Simplextep-1.13.4.dist-info/RECORD
