Metadata-Version: 2.1
Name: Simplextep
Version: 1.13.4
Summary: Simplex implementation with steps.
Home-page: https://github.com/KeivanJamali/simplextep
Author: Keivan Jamali
Author-email: K1Jamali01@gmail.com
License: MIT
License-File: LICENSE
Requires-Dist: numpy
Requires-Dist: pandas
Requires-Dist: tabulate
Requires-Dist: matplotlib
